Seaborn09ZhongwenWendang/README.md
Seaborn09ZhongwenWendang/__init__.py
Seaborn09ZhongwenWendang/__main__.py
Seaborn09ZhongwenWendang/file.epub
Seaborn09ZhongwenWendang/index.html
Seaborn09ZhongwenWendang/css/__init__.py
Seaborn09ZhongwenWendang/css/annotations.css
Seaborn09ZhongwenWendang/css/main.css
Seaborn09ZhongwenWendang/css/normalize.css
Seaborn09ZhongwenWendang/css/popup.css
Seaborn09ZhongwenWendang/font/__init__.py
Seaborn09ZhongwenWendang/font/fontello.eot
Seaborn09ZhongwenWendang/font/fontello.svg
Seaborn09ZhongwenWendang/font/fontello.ttf
Seaborn09ZhongwenWendang/font/fontello.woff
Seaborn09ZhongwenWendang/img/__init__.py
Seaborn09ZhongwenWendang/img/annotator-glyph-sprite.png
Seaborn09ZhongwenWendang/img/annotator-icon-sprite.png
Seaborn09ZhongwenWendang/img/apple-touch-icon.png
Seaborn09ZhongwenWendang/img/cancelfullscreen.png
Seaborn09ZhongwenWendang/img/close.png
Seaborn09ZhongwenWendang/img/fullscreen.png
Seaborn09ZhongwenWendang/img/loader.gif
Seaborn09ZhongwenWendang/img/menu-icon.png
Seaborn09ZhongwenWendang/img/save.png
Seaborn09ZhongwenWendang/img/saved.png
Seaborn09ZhongwenWendang/img/settings-s.png
Seaborn09ZhongwenWendang/img/settings.png
Seaborn09ZhongwenWendang/img/star.png
Seaborn09ZhongwenWendang/js/__init__.py
Seaborn09ZhongwenWendang/js/epub.js
Seaborn09ZhongwenWendang/js/epub.min.js
Seaborn09ZhongwenWendang/js/epub.min.map
Seaborn09ZhongwenWendang/js/hooks.min.js
Seaborn09ZhongwenWendang/js/hooks.min.map
Seaborn09ZhongwenWendang/js/reader.js
Seaborn09ZhongwenWendang/js/reader.js.map
Seaborn09ZhongwenWendang/js/reader.min.js
Seaborn09ZhongwenWendang/js/reader.min.map
Seaborn09ZhongwenWendang/js/hooks/__init__.py
Seaborn09ZhongwenWendang/js/hooks/extensions/__init__.py
Seaborn09ZhongwenWendang/js/hooks/extensions/highlight.js
Seaborn09ZhongwenWendang/js/libs/__init__.py
Seaborn09ZhongwenWendang/js/libs/jquery.min.js
Seaborn09ZhongwenWendang/js/libs/localforage.min.js
Seaborn09ZhongwenWendang/js/libs/screenfull.js
seaborn_0_9_zhongwen_wendang-2024.3.5.0.dist-info/METADATA
seaborn_0_9_zhongwen_wendang-2024.3.5.0.dist-info/WHEEL
seaborn_0_9_zhongwen_wendang-2024.3.5.0.dist-info/entry_points.txt
seaborn_0_9_zhongwen_wendang-2024.3.5.0.dist-info/top_level.txt
seaborn_0_9_zhongwen_wendang-2024.3.5.0.dist-info/RECORD
